djpay/__init__.py
djpay/admin.py
djpay/apps.py
djpay/errors.py
djpay/models.py
djpay/utils.py
djpay/backends/__init__.py
djpay/backends/base.py
djpay/backends/pay_on_delivery.py
djpay/backends/zarinpal.py
djpay/backends/zibal.py
djpay/migrations/0001_initial.py
djpay/migrations/0002_bill_verified.py
djpay/migrations/__init__.py
djpay-0.2.1.dist-info/METADATA
djpay-0.2.1.dist-info/WHEEL
djpay-0.2.1.dist-info/top_level.txt
djpay-0.2.1.dist-info/RECORD
