Metadata-Version: 2.4
Name: djpay
Version: 0.2.1
Summary: A reusable Django app for handling various type of paying methods
Author-email: Kaveh Mehrbanian <mehrbaniankaveh@gmail.com>, Sajjad Daneshmand <Mr.SajjadDaneshmand@gmail.com>
Project-URL: Homepage, https://github.com/kavehkm/DJPay
Project-URL: Documentation, https://github.com/kavehkm/DJPay
Project-URL: Issues, https://github.com/kavehkm/DJPay/issues
Classifier: Programming Language :: Python :: 3
Classifier: License :: OSI Approved :: MIT License
Classifier: Operating System :: OS Independent
Requires-Python: >=3.8
Requires-Dist: django>=5.1.1
Requires-Dist: requests>=2.32.3
